weather/__init__.py
weather/alerts.py
weather/forecast.py
weather/historical_weather.py
weather/latest_weather.py
weather/weather_types.py
weather_usa-1.1.0.dist-info/LICENSE
weather_usa-1.1.0.dist-info/LICENSE.md
weather_usa-1.1.0.dist-info/METADATA
weather_usa-1.1.0.dist-info/WHEEL
weather_usa-1.1.0.dist-info/top_level.txt
weather_usa-1.1.0.dist-info/RECORD
