Metadata-Version: 2.1
Name: weather-usa
Version: 1.1.0
Summary: Wrapper for parts of the IEM and NWS API, built with asyncio for speed
Home-page: https://github.com/Shom770/weather_usa
License: MIT
Platform: UNKNOWN
License-File: LICENSE
License-File: LICENSE.md
Requires-Dist: aiohttp
Requires-Dist: inflection
